syntext/__init__.py
syntext/__main__.py
syntext/inline.py
syntext/interface.py
syntext/nodes.py
syntext/parsers.py
syntext/shorthand.py
syntext/tags.py
syntext/toc.py
syntext/utils.py
syntext-3.1.2.dist-info/METADATA
syntext-3.1.2.dist-info/WHEEL
syntext-3.1.2.dist-info/entry_points.txt
syntext-3.1.2.dist-info/top_level.txt
syntext-3.1.2.dist-info/RECORD
