Metadata-Version: 2.1
Name: syntext
Version: 3.1.2
Summary: A markdownish markup language.
Home-page: http://www.dmulholl.com/docs/syntext/master/
Author: Darren Mulholland
License: Public Domain
Platform: UNKNOWN
Classifier: Programming Language :: Python :: 3
Classifier: Operating System :: OS Independent
Classifier: License :: Public Domain
Classifier: Topic :: Text Processing :: Markup :: HTML
Requires-Dist: pygments
